lunascope/__init__.py
lunascope/__main__.py
lunascope/app.py
lunascope/controller.py
lunascope/helpers.py
lunascope/components/anal.py
lunascope/components/ctree.py
lunascope/components/hypno.py
lunascope/components/masks.py
lunascope/components/metrics.py
lunascope/components/mplcanvas.py
lunascope/components/plts.py
lunascope/components/settings.py
lunascope/components/signals.py
lunascope/components/slist.py
lunascope/components/soappops.py
lunascope/components/spectrogram.py
lunascope/components/tbl_funcs.py
lunascope/ui/main.ui
lunascope-0.2.1.dist-info/METADATA
lunascope-0.2.1.dist-info/WHEEL
lunascope-0.2.1.dist-info/entry_points.txt
lunascope-0.2.1.dist-info/top_level.txt
lunascope-0.2.1.dist-info/RECORD
