Metadata-Version: 2.4
Name: lunascope
Version: 0.2.1
Summary: Sleep-EEG viewer and interface to Luna
Author-email: Lorcan Purcell <lpurcell26@nmhschool.org>, Shaun Purcell <smpurcell@bwh.harvard.edu>, Nataliia Kozhemiako <nkozhemiako@bwh.harvard.edu>
Requires-Python: <3.14,>=3.9
Requires-Dist: lunapi>=1.3.8
Requires-Dist: PySide6>=6.10.0
Requires-Dist: pyqtgraph==0.13.7
Requires-Dist: numpy
Requires-Dist: pandas
Requires-Dist: matplotlib
